momentum/__init__.py
momentum/functions.py
momentum/objects.py
momentum/skatertools/__init__.py
momentum/skatertools/parade.py
momentum-0.2.7.dist-info/LICENSE
momentum-0.2.7.dist-info/METADATA
momentum-0.2.7.dist-info/WHEEL
momentum-0.2.7.dist-info/entry_points.txt
momentum-0.2.7.dist-info/top_level.txt
momentum-0.2.7.dist-info/RECORD
