Metadata-Version: 2.1
Name: momentum
Version: 0.2.7
Summary: Running estimates of moments
Home-page: https://github.com/microprediction/momentum
Author: microprediction
Author-email: pcotton@intechinvestments.com
License: MIT
Platform: UNKNOWN
Classifier: License :: OSI Approved :: MIT License
Classifier: Programming Language :: Python :: 3
Classifier: Programming Language :: Python :: 3.7
Classifier: Programming Language :: Python :: 3.8
Classifier: Programming Language :: Python :: 3.9
License-File: LICENSE
Requires-Dist: wheel
